geo_heatmap/__init__.py
geo_heatmap/console.py
geo_heatmap/generator.py
geo_heatmap/utils.py
geo_heatmap-0.1.5.dist-info/entry_points.txt
geo_heatmap-0.1.5.dist-info/LICENSE
geo_heatmap-0.1.5.dist-info/WHEEL
geo_heatmap-0.1.5.dist-info/METADATA
geo_heatmap-0.1.5.dist-info/RECORD
