Metadata-Version: 2.1
Name: geo-heatmap
Version: 0.1.5
Summary: Generate an interactive geo-heatmap from your Google location data
Home-page: https://github.com/jamesjarvis/geo-heatmap
License: MIT
Author: Luka Steinbach
Author-email: luka.steinbach@gmx.de
Requires-Python: >=3.7,<4.0
Classifier: License :: OSI Approved :: MIT License
Classifier: Programming Language :: Python :: 3
Classifier: Programming Language :: Python :: 3.7
Classifier: Programming Language :: Python :: 3.8
Requires-Dist: argparse (>=1.4.0,<2.0.0)
Requires-Dist: beautifulsoup4 (>=4.8.1,<5.0.0)
Requires-Dist: folium (>=0.10.1,<0.11.0)
Requires-Dist: ijson (>=2.5.1,<3.0.0)
Requires-Dist: progressbar2 (>=3.47.0,<4.0.0)
Project-URL: Repository, https://github.com/jamesjarvis/geo-heatmap
